{"nodes": [{"id": "weights_medicoSAM", "label": "MedicoSAM Pretrained Weights", "file_type": "document", "source_file": "pretrained_weights/MedicoSAM/source.txt", "source_location": null, "source_url": "https://github.com/computational-cell-analytics/medico-sam", "captured_at": null, "author": null, "contributor": null, "rationale": "SAM variant for general medical image segmentation; normalisation: SA-1B statistics (SAM-style); vit_b_medicosam.pt downloadable via wget from owncloud; arxiv 2501.11734"}], "edges": [{"source": "weights_medicoSAM", "target": "weights_SAM", "relation": "conceptually_related_to", "confidence": "INFERRED", "confidence_score": 0.88, "source_file": "pretrained_weights/MedicoSAM/source.txt", "source_location": null, "weight": 0.88}], "hyperedges": []}