{"nodes": [{"id": "img_finetuneCombinationV3", "label": "Fine-tuning Architecture Combination Diagram (v3)", "file_type": "image", "source_file": "finetune_combination_v3.png", "source_location": null, "source_url": null, "captured_at": null, "author": null, "contributor": null, "rationale": "Visualises the 18 fine-tuning strategy combinations: 3 image encoder architectures (ViT-H depth=32, ViT-B depth=12, ViT-Tiny/MobileSAM depth=4, related by distillation) x 2 model components (finetune encoder+decoder vs decoder-only with frozen encoder) x 3 fine-tuning methods (Vanilla full-parameter update, PEFT-Adapter blocks, PEFT-LoRA blocks)"}], "edges": [{"source": "img_finetuneCombinationV3", "target": "method_adapter_finetune", "relation": "references", "confidence": "EXTRACTED", "confidence_score": 1.0, "source_file": "finetune_combination_v3.png", "source_location": "PEFT - update Adapter blocks panel", "weight": 1.0}, {"source": "img_finetuneCombinationV3", "target": "method_lora_finetune", "relation": "references", "confidence": "EXTRACTED", "confidence_score": 1.0, "source_file": "finetune_combination_v3.png", "source_location": "PEFT - update LoRA blocks panel", "weight": 1.0}, {"source": "img_finetuneCombinationV3", "target": "method_vanilla_finetune", "relation": "references", "confidence": "EXTRACTED", "confidence_score": 1.0, "source_file": "finetune_combination_v3.png", "source_location": "Vanilla - update all parameters panel", "weight": 1.0}, {"source": "img_finetuneCombinationV3", "target": "weights_mobileSAM", "relation": "references", "confidence": "EXTRACTED", "confidence_score": 1.0, "source_file": "finetune_combination_v3.png", "source_location": "VIT-Tiny Depth=4 (MobileSAM) with distillation annotation", "weight": 1.0}], "hyperedges": [{"id": "peft_finetuning_method_space", "label": "PEFT and Vanilla Fine-tuning Strategy Space (18 Combinations)", "nodes": ["method_adapter_finetune", "method_lora_finetune", "method_vanilla_finetune", "img_finetuneCombinationV3"], "relation": "implement", "confidence": "EXTRACTED", "confidence_score": 0.95, "source_file": "finetune_combination_v3.png"}]}